{
  "version": "1",
  "packages": [
    {
      "path": "authors",
      "schema": "authors/schema.sql",
      "queries": "authors/query.sql",
      "engine": "postgresql"
    },
    {
      "path": "ondeck",
      "schema": "ondeck/schema",
      "queries": "ondeck/query",
      "engine": "postgresql",
      "emit_json_tags": true,
      "emit_prepared_queries": true
    },
    {
      "path": "jets",
      "schema": "jets/schema.sql",
      "queries": "jets/query-building.sql",
      "engine": "postgresql"
    },
    {
      "name": "booktest",
      "path": "booktest/postgresql",
      "schema": "booktest/postgresql/schema.sql",
      "queries": "booktest/postgresql/query.sql",
      "engine": "postgresql"
    },
    {
      "name": "booktest",
      "path": "booktest/mysql",
      "schema": "booktest/mysql/schema.sql",
      "queries": "booktest/mysql/query.sql",
      "engine": "mysql"
    }
  ]
}
